{
    "ticker": "SDBL",
    "category": "Credit_Rating",
    "extraction_date": "2026-07-01",
    "ai_summary": "SOM Distilleries and Breweries Limited's subsidiaries experienced a credit rating downgrade from BBB to BBB- by ICRA, primarily due to the temporary suspension of operations at the parent company's Bhopal plant. This downgrade could signal higher borrowing costs or restricted credit access for the subsidiaries. While SDBL asserts the impact is not material and the development is interim, the unspecified reasons for the operational suspension at a key plant represent a significant red flag.",
    "source_url": "https://www.bseindia.com/stockinfo/AnnPdfOpen.aspx?Pname=6cc358a9-c427-44a5-b9b6-59500ad16712.pdf",
    "file_type": "pdf"
}